seguridad_nacional/__init__.py
seguridad_nacional/config/__init__.py
seguridad_nacional/config/settings.py
seguridad_nacional/core/__init__.py
seguridad_nacional/core/monitor.py
seguridad_nacional/core/security_manager.py
seguridad_nacional/dashboard/__init__.py
seguridad_nacional/dashboard/routes.py
seguridad_nacional/dashboard/templates.py
seguridad_nacional/detectors/__init__.py
seguridad_nacional/detectors/base.py
seguridad_nacional/detectors/sql_injection.py
seguridad_nacional/detectors/suspicious_behavior.py
seguridad_nacional/detectors/xss.py
seguridad_nacional/middleware/__init__.py
seguridad_nacional/middleware/django_middleware.py
seguridad_nacional/middleware/fastapi_middleware.py
seguridad_nacional/middleware/flask_middleware.py
seguridad_nacional/storage/__init__.py
seguridad_nacional/storage/database.py
seguridad_nacional/utils/__init__.py
seguridad_nacional/utils/blocking.py
seguridad_nacional/utils/geolocation.py
seguridad_nacional-0.1.0.dist-info/licenses/LICENSE
seguridad_nacional-0.1.0.dist-info/METADATA
seguridad_nacional-0.1.0.dist-info/WHEEL
seguridad_nacional-0.1.0.dist-info/top_level.txt
seguridad_nacional-0.1.0.dist-info/RECORD
