Metadata-Version: 2.4
Name: seguridad-nacional
Version: 0.1.0
Summary: Librería de seguridad para monitoreo y protección de endpoints en aplicaciones Python
Home-page: https://github.com/hackathon-team/seguridad-nacional
Author: Hackathon Team - Key Institute
Author-email: Hackathon Team <hackathon@keyinstitute.sv>
License: MIT
Project-URL: Homepage, https://github.com/hackathon-team/seguridad-nacional
Project-URL: Documentation, https://github.com/hackathon-team/seguridad-nacional#readme
Project-URL: Repository, https://github.com/hackathon-team/seguridad-nacional
Keywords: security,cybersecurity,web-security,fastapi,flask,django,sql-injection,xss
Classifier: Development Status :: 3 - Alpha
Classifier: Intended Audience :: Developers
Classifier: Topic :: Security
Classifier: License :: OSI Approved :: MIT License
Classifier: Programming Language :: Python :: 3
Classifier: Programming Language :: Python :: 3.8
Classifier: Programming Language :: Python :: 3.9
Classifier: Programming Language :: Python :: 3.10
Classifier: Programming Language :: Python :: 3.11
Requires-Python: >=3.8
License-File: LICENSE
Dynamic: author
Dynamic: home-page
Dynamic: license-file
Dynamic: requires-python
